{
  "map": [
    [
      {
        "x": 0,
        "y": 0,
        "elevation": 0,
        "terrain": "water",
        "resources": {}
      },
      {
        "x": 1,
        "y": 0,
        "elevation": 0,
        "terrain": "water",
        "resources": {}
      },
      {
        "x": 2,
        "y": 0,
        "elevation": 0,
        "terrain": "water",
        "resources": {}
      },
      {
        "x": 3,
        "y": 0,
        "elevation": 0,
        "terrain": "water",
        "resources": {}
      },
      {
        "x": 4,
        "y": 0,
        "elevation": 0,
        "terrain": "water",
        "resources": {}
      },
      {
        "x": 5,
        "y": 0,
        "elevation": 0.0035750595336142403,
        "terrain": "water",
        "resources": {}
      },
      {
        "x": 6,
        "y": 0,
        "elevation": 0.03380438210954208,
        "terrain": "water",
        "resources": {}
      },
      {
        "x": 7,
        "y": 0,
        "elevation": 0.051061897892219786,
        "terrain": "water",
        "resources": {}
      },
      {
        "x": 8,
        "y": 0,
        "elevation": 0.06955648217434068,
        "terrain": "water",
        "resources": {}
      },
      {
        "x": 9,
        "y": 0,
        "elevation": 0.08532052261708742,
        "terrain": "water",
        "resources": {}
      },
      {
        "x": 10,
        "y": 0,
        "elevation": 0.07565144490545407,
        "terrain": "water",
        "resources": {}
      },
      {
        "x": 11,
        "y": 0,
        "elevation": 0.05788321423391265,
        "terrain": "water",
        "resources": {}
      },
      {
        "x": 12,
        "y": 0,
        "elevation": 0.05799049993201759,
        "terrain": "water",
        "resources": {}
      },
      {
        "x": 13,
        "y": 0,
        "elevation": 0.034734642061162946,
        "terrain": "water",
        "resources": {}
      },
      {
        "x": 14,
        "y": 0,
        "elevation": 0.0040921796592567885,
        "terrain": "water",
        "resources": {}
      },
      {
        "x": 15,
        "y": 0,
        "elevation": 0,
        "terrain": "water",
        "resources": {}
      },
      {
        "x": 16,
        "y": 0,
        "elevation": 0,
        "terrain": "water",
        "resources": {}
      },
      {
        "x": 17,
        "y": 0,
        "elevation": 0,
        "terrain": "water",
        "resources": {}
      },
      {
        "x": 18,
        "y": 0,
        "elevation": 0,
        "terrain": "water",
        "resources": {}
      },
      {
        "x": 19,
        "y": 0,
        "elevation": 0,
        "terrain": "water",
        "resources": {}
      }
    ],
    [
      {
        "x": 0,
        "y": 1,
        "elevation": 0,
        "terrain": "water",
        "resources": {}
      },
      {
        "x": 1,
        "y": 1,
        "elevation": 0,
        "terrain": "water",
        "resources": {}
      },
      {
        "x": 2,
        "y": 1,
        "elevation": 0,
        "terrain": "water",
        "resources": {}
      },
      {
        "x": 3,
        "y": 1,
        "elevation": 0,
        "terrain": "water",
        "resources": {}
      },
      {
        "x": 4,
        "y": 1,
        "elevation": 0.03406482488129593,
        "terrain": "water",
        "resources": {}
      },
      {
        "x": 5,
        "y": 1,
        "elevation": 0.0878304825938367,
        "terrain": "water",
        "resources": {}
      },
      {
        "x": 6,
        "y": 1,
        "elevation": 0.10254731058449003,
        "terrain": "water",
        "resources": {}
      },
      {
        "x": 7,
        "y": 1,
        "elevation": 0.1161875254248208,
        "terrain": "water",
        "resources": {}
      },
      {
        "x": 8,
        "y": 1,
        "elevation": 0.12821991019520837,
        "terrain": "water",
        "resources": {}
      },
      {
        "x": 9,
        "y": 1,
        "elevation": 0.13393191555328254,
        "terrain": "water",
        "resources": {}
      },
      {
        "x": 10,
        "y": 1,
        "elevation": 0.12809978433292474,
        "terrain": "water",
        "resources": {}
      },
      {
        "x": 11,
        "y": 1,
        "elevation": 0.1138179207680832,
        "terrain": "water",
        "resources": {}
      },
      {
        "x": 12,
        "y": 1,
        "elevation": 0.11843993171739865,
        "terrain": "water",
        "resources": {}
      },
      {
        "x": 13,
        "y": 1,
        "elevation": 0.11699369907781398,
        "terrain": "water",
        "resources": {}
      },
      {
        "x": 14,
        "y": 1,
        "elevation": 0.08828707267692369,
        "terrain": "water",
        "resources": {}
      },
      {
        "x": 15,
        "y": 1,
        "elevation": 0.040271338188726594,
        "terrain": "water",
        "resources": {}
      },
      {
        "x": 16,
        "y": 1,
        "elevation": 0,
        "terrain": "water",
        "resources": {}
      },
      {
        "x": 17,
        "y": 1,
        "elevation": 0,
        "terrain": "water",
        "resources": {}
      },
      {
        "x": 18,
        "y": 1,
        "elevation": 0,
        "terrain": "water",
        "resources": {}
      },
      {
        "x": 19,
        "y": 1,
        "elevation": 0,
        "terrain": "water",
        "resources": {}
      }
    ],
    [
      {
        "x": 0,
        "y": 2,
        "elevation": 0,
        "terrain": "water",
        "resources": {}
      },
      {
        "x": 1,
        "y": 2,
        "elevation": 0,
        "terrain": "water",
        "resources": {}
      },
      {
        "x": 2,
        "y": 2,
        "elevation": 0,
        "terrain": "water",
        "resources": {}
      },
      {
        "x": 3,
        "y": 2,
        "elevation": 0.04859988741236073,
        "terrain": "water",
        "resources": {}
      },
      {
        "x": 4,
        "y": 2,
        "elevation": 0.09870806431352319,
        "terrain": "water",
        "resources": {}
      },
      {
        "x": 5,
        "y": 2,
        "elevation": 0.14786019150455068,
        "terrain": "water",
        "resources": {}
      },
      {
        "x": 6,
        "y": 2,
        "elevation": 0.14602118168361464,
        "terrain": "water",
        "resources": {}
      },
      {
        "x": 7,
        "y": 2,
        "elevation": 0.15831776520534302,
        "terrain": "water",
        "resources": {}
      },
      {
        "x": 8,
        "y": 2,
        "elevation": 0.17203324868436032,
        "terrain": "water",
        "resources": {}
      },
      {
        "x": 9,
        "y": 2,
        "elevation": 0.17690612832352898,
        "terrain": "water",
        "resources": {}
      },
      {
        "x": 10,
        "y": 2,
        "elevation": 0.23050309982056386,
        "terrain": "water",
        "resources": {}
      },
      {
        "x": 11,
        "y": 2,
        "elevation": 0.24719955938258717,
        "terrain": "water",
        "resources": {}
      },
      {
        "x": 12,
        "y": 2,
        "elevation": 0.21263097127549932,
        "terrain": "water",
        "resources": {}
      },
      {
        "x": 13,
        "y": 2,
        "elevation": 0.21887414383425452,
        "terrain": "water",
        "resources": {}
      },
      {
        "x": 14,
        "y": 2,
        "elevation": 0.16243632752626544,
        "terrain": "water",
        "resources": {}
      },
      {
        "x": 15,
        "y": 2,
        "elevation": 0.11084139997718663,
        "terrain": "water",
        "resources": {}
      },
      {
        "x": 16,
        "y": 2,
        "elevation": 0.06152216213371515,
        "terrain": "water",
        "resources": {}
      },
      {
        "x": 17,
        "y": 2,
        "elevation": 0,
        "terrain": "water",
        "resources": {}
      },
      {
        "x": 18,
        "y": 2,
        "elevation": 0,
        "terrain": "water",
        "resources": {}
      },
      {
        "x": 19,
        "y": 2,
        "elevation": 0,
        "terrain": "water",
        "resources": {}
      }
    ],
    [
      {
        "x": 0,
        "y": 3,
        "elevation": 0,
        "terrain": "water",
        "resources": {}
      },
      {
        "x": 1,
        "y": 3,
        "elevation": 0,
        "terrain": "water",
        "resources": {}
      },
      {
        "x": 2,
        "y": 3,
        "elevation": 0.043250725639912196,
        "terrain": "water",
        "resources": {}
      },
      {
        "x": 3,
        "y": 3,
        "elevation": 0.10741876869289839,
        "terrain": "water",
        "resources": {}
      },
      {
        "x": 4,
        "y": 3,
        "elevation": 0.17828291863158843,
        "terrain": "water",
        "resources": {}
      },
      {
        "x": 5,
        "y": 3,
        "elevation": 0.2244589776187092,
        "terrain": "water",
        "resources": {}
      },
      {
        "x": 6,
        "y": 3,
        "elevation": 0.2443383551137864,
        "terrain": "water",
        "resources": {}
      },
      {
        "x": 7,
        "y": 3,
        "elevation": 0.1789225523423284,
        "terrain": "water",
        "resources": {}
      },
      {
        "x": 8,
        "y": 3,
        "elevation": 0.24354127944888784,
        "terrain": "water",
        "resources": {}
      },
      {
        "x": 9,
        "y": 3,
        "elevation": 0.24592291060432736,
        "terrain": "water",
        "resources": {}
      },
      {
        "x": 10,
        "y": 3,
        "elevation": 0.30409446382688526,
        "terrain": "beach",
        "resources": {}
      },
      {
        "x": 11,
        "y": 3,
        "elevation": 0.2909428261735024,
        "terrain": "beach",
        "resources": {}
      },
      {
        "x": 12,
        "y": 3,
        "elevation": 0.2787982130785394,
        "terrain": "beach",
        "resources": {}
      },
      {
        "x": 13,
        "y": 3,
        "elevation": 0.2636143127915041,
        "terrain": "beach",
        "resources": {}
      },
      {
        "x": 14,
        "y": 3,
        "elevation": 0.22084201540970447,
        "terrain": "water",
        "resources": {}
      },
      {
        "x": 15,
        "y": 3,
        "elevation": 0.150676128166408,
        "terrain": "water",
        "resources": {}
      },
      {
        "x": 16,
        "y": 3,
        "elevation": 0.1156092324375524,
        "terrain": "water",
        "resources": {}
      },
      {
        "x": 17,
        "y": 3,
        "elevation": 0.061975571310095894,
        "terrain": "water",
        "resources": {}
      },
      {
        "x": 18,
        "y": 3,
        "elevation": 0,
        "terrain": "water",
        "resources": {}
      },
      {
        "x": 19,
        "y": 3,
        "elevation": 0,
        "terrain": "water",
        "resources": {}
      }
    ],
    [
      {
        "x": 0,
        "y": 4,
        "elevation": 0,
        "terrain": "water",
        "resources": {}
      },
      {
        "x": 1,
        "y": 4,
        "elevation": 0.03371329402000972,
        "terrain": "water",
        "resources": {}
      },
      {
        "x": 2,
        "y": 4,
        "elevation": 0.08270298475304255,
        "terrain": "water",
        "resources": {}
      },
      {
        "x": 3,
        "y": 4,
        "elevation": 0.14559534652037215,
        "terrain": "water",
        "resources": {}
      },
      {
        "x": 4,
        "y": 4,
        "elevation": 0.2075146957607554,
        "terrain": "water",
        "resources": {}
      },
      {
        "x": 5,
        "y": 4,
        "elevation": 0.2719864066347823,
        "terrain": "beach",
        "resources": {}
      },
      {
        "x": 6,
        "y": 4,
        "elevation": 0.2816180010957907,
        "terrain": "beach",
        "resources": {}
      },
      {
        "x": 7,
        "y": 4,
        "elevation": 0.2631389355113143,
        "terrain": "beach",
        "resources": {}
      },
      {
        "x": 8,
        "y": 4,
        "elevation": 0.2865260449596324,
        "terrain": "beach",
        "resources": {}
      },
      {
        "x": 9,
        "y": 4,
        "elevation": 0.3713306815417923,
        "terrain": "grass",
        "resources": {}
      },
      {
        "x": 10,
        "y": 4,
        "elevation": 0.32556445641847775,
        "terrain": "grass",
        "resources": {}
      },
      {
        "x": 11,
        "y": 4,
        "elevation": 0.3027789372921662,
        "terrain": "beach",
        "resources": {}
      },
      {
        "x": 12,
        "y": 4,
        "elevation": 0.3215483429335718,
        "terrain": "grass",
        "resources": {}
      },
      {
        "x": 13,
        "y": 4,
        "elevation": 0.3082841597748752,
        "terrain": "beach",
        "resources": {}
      },
      {
        "x": 14,
        "y": 4,
        "elevation": 0.2731745019259446,
        "terrain": "beach",
        "resources": {}
      },
      {
        "x": 15,
        "y": 4,
        "elevation": 0.21338483537639663,
        "terrain": "water",
        "resources": {}
      },
      {
        "x": 16,
        "y": 4,
        "elevation": 0.16946623641189876,
        "terrain": "water",
        "resources": {}
      },
      {
        "x": 17,
        "y": 4,
        "elevation": 0.11631816610263375,
        "terrain": "water",
        "resources": {}
      },
      {
        "x": 18,
        "y": 4,
        "elevation": 0.041692767261478456,
        "terrain": "water",
        "resources": {}
      },
      {
        "x": 19,
        "y": 4,
        "elevation": 0,
        "terrain": "water",
        "resources": {}
      }
    ],
    [
      {
        "x": 0,
        "y": 5,
        "elevation": 0.0031764090665179407,
        "terrain": "water",
        "resources": {}
      },
      {
        "x": 1,
        "y": 5,
        "elevation": 0.0725846020558712,
        "terrain": "water",
        "resources": {}
      },
      {
        "x": 2,
        "y": 5,
        "elevation": 0.11975099945985591,
        "terrain": "water",
        "resources": {}
      },
      {
        "x": 3,
        "y": 5,
        "elevation": 0.1690040917551274,
        "terrain": "water",
        "resources": {}
      },
      {
        "x": 4,
        "y": 5,
        "elevation": 0.20948714961135084,
        "terrain": "water",
        "resources": {}
      },
      {
        "x": 5,
        "y": 5,
        "elevation": 0.27911895621631405,
        "terrain": "beach",
        "resources": {}
      },
      {
        "x": 6,
        "y": 5,
        "elevation": 0.28665241505878636,
        "terrain": "beach",
        "resources": {}
      },
      {
        "x": 7,
        "y": 5,
        "elevation": 0.35598490535086585,
        "terrain": "grass",
        "resources": {}
      },
      {
        "x": 8,
        "y": 5,
        "elevation": 0.4482098739455207,
        "terrain": "grass",
        "resources": {}
      },
      {
        "x": 9,
        "y": 5,
        "elevation": 0.5035276610030459,
        "terrain": "forest",
        "resources": {}
      },
      {
        "x": 10,
        "y": 5,
        "elevation": 0.35745704871255884,
        "terrain": "grass",
        "resources": {}
      },
      {
        "x": 11,
        "y": 5,
        "elevation": 0.28884151892953314,
        "terrain": "beach",
        "resources": {}
      },
      {
        "x": 12,
        "y": 5,
        "elevation": 0.3627331262932092,
        "terrain": "grass",
        "resources": {}
      },
      {
        "x": 13,
        "y": 5,
        "elevation": 0.29417032853852143,
        "terrain": "beach",
        "resources": {}
      },
      {
        "x": 14,
        "y": 5,
        "elevation": 0.27755801912770584,
        "terrain": "beach",
        "resources": {}
      },
      {
        "x": 15,
        "y": 5,
        "elevation": 0.1709082671067527,
        "terrain": "water",
        "resources": {}
      },
      {
        "x": 16,
        "y": 5,
        "elevation": 0.1798990332934501,
        "terrain": "water",
        "resources": {}
      },
      {
        "x": 17,
        "y": 5,
        "elevation": 0.13282731991588728,
        "terrain": "water",
        "resources": {}
      },
      {
        "x": 18,
        "y": 5,
        "elevation": 0.0892442767298969,
        "terrain": "water",
        "resources": {}
      },
      {
        "x": 19,
        "y": 5,
        "elevation": 0.0040550530332653465,
        "terrain": "water",
        "resources": {}
      }
    ],
    [
      {
        "x": 0,
        "y": 6,
        "elevation": 0.03332414690971535,
        "terrain": "water",
        "resources": {}
      },
      {
        "x": 1,
        "y": 6,
        "elevation": 0.10640521270222725,
        "terrain": "water",
        "resources": {}
      },
      {
        "x": 2,
        "y": 6,
        "elevation": 0.16005065408040964,
        "terrain": "water",
        "resources": {}
      },
      {
        "x": 3,
        "y": 6,
        "elevation": 0.183568847043499,
        "terrain": "water",
        "resources": {}
      },
      {
        "x": 4,
        "y": 6,
        "elevation": 0.21567961238949204,
        "terrain": "water",
        "resources": {}
      },
      {
        "x": 5,
        "y": 6,
        "elevation": 0.2718895503806696,
        "terrain": "beach",
        "resources": {}
      },
      {
        "x": 6,
        "y": 6,
        "elevation": 0.37612309118820875,
        "terrain": "grass",
        "resources": {}
      },
      {
        "x": 7,
        "y": 6,
        "elevation": 0.36864844853321255,
        "terrain": "grass",
        "resources": {}
      },
      {
        "x": 8,
        "y": 6,
        "elevation": 0.44173328456437244,
        "terrain": "grass",
        "resources": {
          "water": 1
        }
      },
      {
        "x": 9,
        "y": 6,
        "elevation": 0.39322017933475856,
        "terrain": "grass",
        "resources": {}
      },
      {
        "x": 10,
        "y": 6,
        "elevation": 0.4593502519219942,
        "terrain": "forest",
        "resources": {}
      },
      {
        "x": 11,
        "y": 6,
        "elevation": 0.4035472476854304,
        "terrain": "grass",
        "resources": {}
      },
      {
        "x": 12,
        "y": 6,
        "elevation": 0.3729092493963933,
        "terrain": "grass",
        "resources": {}
      },
      {
        "x": 13,
        "y": 6,
        "elevation": 0.27832977512778917,
        "terrain": "beach",
        "resources": {}
      },
      {
        "x": 14,
        "y": 6,
        "elevation": 0.30660607018932834,
        "terrain": "beach",
        "resources": {}
      },
      {
        "x": 15,
        "y": 6,
        "elevation": 0.3434149750973014,
        "terrain": "grass",
        "resources": {}
      },
      {
        "x": 16,
        "y": 6,
        "elevation": 0.2363083418963365,
        "terrain": "water",
        "resources": {}
      },
      {
        "x": 17,
        "y": 6,
        "elevation": 0.17836081318441627,
        "terrain": "water",
        "resources": {}
      },
      {
        "x": 18,
        "y": 6,
        "elevation": 0.09543372516247939,
        "terrain": "water",
        "resources": {}
      },
      {
        "x": 19,
        "y": 6,
        "elevation": 0.03515542185136778,
        "terrain": "water",
        "resources": {}
      }
    ],
    [
      {
        "x": 0,
        "y": 7,
        "elevation": 0.04642609117310601,
        "terrain": "water",
        "resources": {}
      },
      {
        "x": 1,
        "y": 7,
        "elevation": 0.11792287359439982,
        "terrain": "water",
        "resources": {}
      },
      {
        "x": 2,
        "y": 7,
        "elevation": 0.19481250989594412,
        "terrain": "water",
        "resources": {}
      },
      {
        "x": 3,
        "y": 7,
        "elevation": 0.2501266344621007,
        "terrain": "beach",
        "resources": {}
      },
      {
        "x": 4,
        "y": 7,
        "elevation": 0.29332999160062967,
        "terrain": "beach",
        "resources": {}
      },
      {
        "x": 5,
        "y": 7,
        "elevation": 0.3163958782512516,
        "terrain": "beach",
        "resources": {}
      },
      {
        "x": 6,
        "y": 7,
        "elevation": 0.2897514920771443,
        "terrain": "beach",
        "resources": {}
      },
      {
        "x": 7,
        "y": 7,
        "elevation": 0.3372618818223954,
        "terrain": "grass",
        "resources": {}
      },
      {
        "x": 8,
        "y": 7,
        "elevation": 0.395732681270574,
        "terrain": "grass",
        "resources": {}
      },
      {
        "x": 9,
        "y": 7,
        "elevation": 0.4417844273032024,
        "terrain": "grass",
        "resources": {}
      },
      {
        "x": 10,
        "y": 7,
        "elevation": 0.5223913713362947,
        "terrain": "forest",
        "resources": {}
      },
      {
        "x": 11,
        "y": 7,
        "elevation": 0.4779827798397104,
        "terrain": "forest",
        "resources": {}
      },
      {
        "x": 12,
        "y": 7,
        "elevation": 0.43389617050476237,
        "terrain": "grass",
        "resources": {}
      },
      {
        "x": 13,
        "y": 7,
        "elevation": 0.37909397846525344,
        "terrain": "grass",
        "resources": {}
      },
      {
        "x": 14,
        "y": 7,
        "elevation": 0.3263051585101023,
        "terrain": "grass",
        "resources": {}
      },
      {
        "x": 15,
        "y": 7,
        "elevation": 0.33926476254606636,
        "terrain": "grass",
        "resources": {}
      },
      {
        "x": 16,
        "y": 7,
        "elevation": 0.2617962936857735,
        "terrain": "beach",
        "resources": {}
      },
      {
        "x": 17,
        "y": 7,
        "elevation": 0.19604353303690863,
        "terrain": "water",
        "resources": {}
      },
      {
        "x": 18,
        "y": 7,
        "elevation": 0.1083034670575494,
        "terrain": "water",
        "resources": {}
      },
      {
        "x": 19,
        "y": 7,
        "elevation": 0.049139965126706285,
        "terrain": "water",
        "resources": {}
      }
    ],
    [
      {
        "x": 0,
        "y": 8,
        "elevation": 0.06955648217434068,
        "terrain": "water",
        "resources": {}
      },
      {
        "x": 1,
        "y": 8,
        "elevation": 0.12591414293706665,
        "terrain": "water",
        "resources": {}
      },
      {
        "x": 2,
        "y": 8,
        "elevation": 0.1997365244918529,
        "terrain": "water",
        "resources": {}
      },
      {
        "x": 3,
        "y": 8,
        "elevation": 0.28457515878388207,
        "terrain": "beach",
        "resources": {}
      },
      {
        "x": 4,
        "y": 8,
        "elevation": 0.330606974953422,
        "terrain": "grass",
        "resources": {}
      },
      {
        "x": 5,
        "y": 8,
        "elevation": 0.33363244405655357,
        "terrain": "grass",
        "resources": {}
      },
      {
        "x": 6,
        "y": 8,
        "elevation": 0.39954836009963257,
        "terrain": "grass",
        "resources": {}
      },
      {
        "x": 7,
        "y": 8,
        "elevation": 0.4199523217939163,
        "terrain": "grass",
        "resources": {}
      },
      {
        "x": 8,
        "y": 8,
        "elevation": 0.47529297098810475,
        "terrain": "forest",
        "resources": {}
      },
      {
        "x": 9,
        "y": 8,
        "elevation": 0.5061578808794688,
        "terrain": "forest",
        "resources": {}
      },
      {
        "x": 10,
        "y": 8,
        "elevation": 0.532059704612149,
        "terrain": "forest",
        "resources": {}
      },
      {
        "x": 11,
        "y": 8,
        "elevation": 0.580880109025485,
        "terrain": "rocky",
        "resources": {}
      },
      {
        "x": 12,
        "y": 8,
        "elevation": 0.4536752176079724,
        "terrain": "forest",
        "resources": {
          "wood": 2
        }
      },
      {
        "x": 13,
        "y": 8,
        "elevation": 0.38329559491024495,
        "terrain": "grass",
        "resources": {}
      },
      {
        "x": 14,
        "y": 8,
        "elevation": 0.3853269934038907,
        "terrain": "grass",
        "resources": {}
      },
      {
        "x": 15,
        "y": 8,
        "elevation": 0.36745587737010554,
        "terrain": "grass",
        "resources": {}
      },
      {
        "x": 16,
        "y": 8,
        "elevation": 0.2732145645647762,
        "terrain": "beach",
        "resources": {}
      },
      {
        "x": 17,
        "y": 8,
        "elevation": 0.1951686398370799,
        "terrain": "water",
        "resources": {}
      },
      {
        "x": 18,
        "y": 8,
        "elevation": 0.10453960862333726,
        "terrain": "water",
        "resources": {}
      },
      {
        "x": 19,
        "y": 8,
        "elevation": 0.056222417369496014,
        "terrain": "water",
        "resources": {}
      }
    ],
    [
      {
        "x": 0,
        "y": 9,
        "elevation": 0.07334155990475716,
        "terrain": "water",
        "resources": {}
      },
      {
        "x": 1,
        "y": 9,
        "elevation": 0.15369251339056406,
        "terrain": "water",
        "resources": {}
      },
      {
        "x": 2,
        "y": 9,
        "elevation": 0.22153520398303148,
        "terrain": "water",
        "resources": {}
      },
      {
        "x": 3,
        "y": 9,
        "elevation": 0.30971724308452014,
        "terrain": "beach",
        "resources": {}
      },
      {
        "x": 4,
        "y": 9,
        "elevation": 0.3353061510529106,
        "terrain": "grass",
        "resources": {}
      },
      {
        "x": 5,
        "y": 9,
        "elevation": 0.3687157642132327,
        "terrain": "grass",
        "resources": {}
      },
      {
        "x": 6,
        "y": 9,
        "elevation": 0.46162137574905826,
        "terrain": "forest",
        "resources": {}
      },
      {
        "x": 7,
        "y": 9,
        "elevation": 0.4822799125016441,
        "terrain": "forest",
        "resources": {}
      },
      {
        "x": 8,
        "y": 9,
        "elevation": 0.49237008607401134,
        "terrain": "forest",
        "resources": {}
      },
      {
        "x": 9,
        "y": 9,
        "elevation": 0.5345963392066593,
        "terrain": "forest",
        "resources": {}
      },
      {
        "x": 10,
        "y": 9,
        "elevation": 0.549440646973205,
        "terrain": "forest",
        "resources": {}
      },
      {
        "x": 11,
        "y": 9,
        "elevation": 0.500192603295012,
        "terrain": "forest",
        "resources": {
          "wood": 1
        }
      },
      {
        "x": 12,
        "y": 9,
        "elevation": 0.45800564523689996,
        "terrain": "forest",
        "resources": {}
      },
      {
        "x": 13,
        "y": 9,
        "elevation": 0.4928202203021433,
        "terrain": "forest",
        "resources": {}
      },
      {
        "x": 14,
        "y": 9,
        "elevation": 0.3933516966583315,
        "terrain": "grass",
        "resources": {}
      },
      {
        "x": 15,
        "y": 9,
        "elevation": 0.34181652179069144,
        "terrain": "grass",
        "resources": {}
      },
      {
        "x": 16,
        "y": 9,
        "elevation": 0.22041134490774014,
        "terrain": "water",
        "resources": {}
      },
      {
        "x": 17,
        "y": 9,
        "elevation": 0.12841720159491546,
        "terrain": "water",
        "resources": {}
      },
      {
        "x": 18,
        "y": 9,
        "elevation": 0.10216768714236706,
        "terrain": "water",
        "resources": {}
      },
      {
        "x": 19,
        "y": 9,
        "elevation": 0.050670364699774095,
        "terrain": "water",
        "resources": {}
      }
    ],
    [
      {
        "x": 0,
        "y": 10,
        "elevation": 0.08861710272796841,
        "terrain": "water",
        "resources": {}
      },
      {
        "x": 1,
        "y": 10,
        "elevation": 0.1557755319993358,
        "terrain": "water",
        "resources": {}
      },
      {
        "x": 2,
        "y": 10,
        "elevation": 0.1963225722105,
        "terrain": "water",
        "resources": {}
      },
      {
        "x": 3,
        "y": 10,
        "elevation": 0.2915252344944828,
        "terrain": "beach",
        "resources": {}
      },
      {
        "x": 4,
        "y": 10,
        "elevation": 0.269999741853761,
        "terrain": "beach",
        "resources": {}
      },
      {
        "x": 5,
        "y": 10,
        "elevation": 0.24690002809326728,
        "terrain": "water",
        "resources": {}
      },
      {
        "x": 6,
        "y": 10,
        "elevation": 0.3675215463040731,
        "terrain": "grass",
        "resources": {}
      },
      {
        "x": 7,
        "y": 10,
        "elevation": 0.4062090219161941,
        "terrain": "grass",
        "resources": {}
      },
      {
        "x": 8,
        "y": 10,
        "elevation": 0.525348813525894,
        "terrain": "forest",
        "resources": {}
      },
      {
        "x": 9,
        "y": 10,
        "elevation": 0.5233161738716132,
        "terrain": "forest",
        "resources": {}
      },
      {
        "x": 10,
        "y": 10,
        "elevation": 0.5631806719625774,
        "terrain": "rocky",
        "resources": {}
      },
      {
        "x": 11,
        "y": 10,
        "elevation": 0.6071931951462362,
        "terrain": "rocky",
        "resources": {}
      },
      {
        "x": 12,
        "y": 10,
        "elevation": 0.5156959127729679,
        "terrain": "forest",
        "resources": {}
      },
      {
        "x": 13,
        "y": 10,
        "elevation": 0.48353262783794027,
        "terrain": "forest",
        "resources": {}
      },
      {
        "x": 14,
        "y": 10,
        "elevation": 0.3833858927449511,
        "terrain": "grass",
        "resources": {}
      },
      {
        "x": 15,
        "y": 10,
        "elevation": 0.38615691287244547,
        "terrain": "grass",
        "resources": {}
      },
      {
        "x": 16,
        "y": 10,
        "elevation": 0.3183219869967578,
        "terrain": "beach",
        "resources": {}
      },
      {
        "x": 17,
        "y": 10,
        "elevation": 0.19560923522969592,
        "terrain": "water",
        "resources": {}
      },
      {
        "x": 18,
        "y": 10,
        "elevation": 0.11983792726994931,
        "terrain": "water",
        "resources": {}
      },
      {
        "x": 19,
        "y": 10,
        "elevation": 0.051301666576897255,
        "terrain": "water",
        "resources": {}
      }
    ],
    [
      {
        "x": 0,
        "y": 11,
        "elevation": 0.07789471264853604,
        "terrain": "water",
        "resources": {}
      },
      {
        "x": 1,
        "y": 11,
        "elevation": 0.14778289915525725,
        "terrain": "water",
        "resources": {}
      },
      {
        "x": 2,
        "y": 11,
        "elevation": 0.19369417125761101,
        "terrain": "water",
        "resources": {}
      },
      {
        "x": 3,
        "y": 11,
        "elevation": 0.2910267662317737,
        "terrain": "beach",
        "resources": {}
      },
      {
        "x": 4,
        "y": 11,
        "elevation": 0.2673146264647194,
        "terrain": "beach",
        "resources": {}
      },
      {
        "x": 5,
        "y": 11,
        "elevation": 0.30974372732504957,
        "terrain": "beach",
        "resources": {}
      },
      {
        "x": 6,
        "y": 11,
        "elevation": 0.3878140935646354,
        "terrain": "grass",
        "resources": {}
      },
      {
        "x": 7,
        "y": 11,
        "elevation": 0.41033077144255,
        "terrain": "grass",
        "resources": {}
      },
      {
        "x": 8,
        "y": 11,
        "elevation": 0.4746528262395815,
        "terrain": "forest",
        "resources": {
          "wood": 3
        }
      },
      {
        "x": 9,
        "y": 11,
        "elevation": 0.46670807358803784,
        "terrain": "forest",
        "resources": {
          "wood": 3
        }
      },
      {
        "x": 10,
        "y": 11,
        "elevation": 0.38727611019569785,
        "terrain": "grass",
        "resources": {}
      },
      {
        "x": 11,
        "y": 11,
        "elevation": 0.4646990793966559,
        "terrain": "forest",
        "resources": {}
      },
      {
        "x": 12,
        "y": 11,
        "elevation": 0.5623622389633606,
        "terrain": "rocky",
        "resources": {}
      },
      {
        "x": 13,
        "y": 11,
        "elevation": 0.4234705116239078,
        "terrain": "grass",
        "resources": {}
      },
      {
        "x": 14,
        "y": 11,
        "elevation": 0.3907455958833353,
        "terrain": "grass",
        "resources": {}
      },
      {
        "x": 15,
        "y": 11,
        "elevation": 0.33029124163095464,
        "terrain": "grass",
        "resources": {}
      },
      {
        "x": 16,
        "y": 11,
        "elevation": 0.275483014755997,
        "terrain": "beach",
        "resources": {}
      },
      {
        "x": 17,
        "y": 11,
        "elevation": 0.24253592197277243,
        "terrain": "water",
        "resources": {}
      },
      {
        "x": 18,
        "y": 11,
        "elevation": 0.129831440494769,
        "terrain": "water",
        "resources": {}
      },
      {
        "x": 19,
        "y": 11,
        "elevation": 0.049527615575224254,
        "terrain": "water",
        "resources": {}
      }
    ],
    [
      {
        "x": 0,
        "y": 12,
        "elevation": 0.05436609368626649,
        "terrain": "water",
        "resources": {}
      },
      {
        "x": 1,
        "y": 12,
        "elevation": 0.13136342195377482,
        "terrain": "water",
        "resources": {}
      },
      {
        "x": 2,
        "y": 12,
        "elevation": 0.19143290655887943,
        "terrain": "water",
        "resources": {}
      },
      {
        "x": 3,
        "y": 12,
        "elevation": 0.26075870664453943,
        "terrain": "beach",
        "resources": {}
      },
      {
        "x": 4,
        "y": 12,
        "elevation": 0.3008032885507607,
        "terrain": "beach",
        "resources": {}
      },
      {
        "x": 5,
        "y": 12,
        "elevation": 0.3971832267275413,
        "terrain": "grass",
        "resources": {}
      },
      {
        "x": 6,
        "y": 12,
        "elevation": 0.39319563788487594,
        "terrain": "grass",
        "resources": {}
      },
      {
        "x": 7,
        "y": 12,
        "elevation": 0.36528760940044835,
        "terrain": "grass",
        "resources": {}
      },
      {
        "x": 8,
        "y": 12,
        "elevation": 0.3931851885935761,
        "terrain": "grass",
        "resources": {}
      },
      {
        "x": 9,
        "y": 12,
        "elevation": 0.395071581035753,
        "terrain": "grass",
        "resources": {}
      },
      {
        "x": 10,
        "y": 12,
        "elevation": 0.35607358949366574,
        "terrain": "grass",
        "resources": {}
      },
      {
        "x": 11,
        "y": 12,
        "elevation": 0.4475852333025985,
        "terrain": "grass",
        "resources": {}
      },
      {
        "x": 12,
        "y": 12,
        "elevation": 0.4756161187464476,
        "terrain": "forest",
        "resources": {}
      },
      {
        "x": 13,
        "y": 12,
        "elevation": 0.3533534939875212,
        "terrain": "grass",
        "resources": {}
      },
      {
        "x": 14,
        "y": 12,
        "elevation": 0.31558897372143474,
        "terrain": "beach",
        "resources": {}
      },
      {
        "x": 15,
        "y": 12,
        "elevation": 0.28652840188622136,
        "terrain": "beach",
        "resources": {}
      },
      {
        "x": 16,
        "y": 12,
        "elevation": 0.23770043962058043,
        "terrain": "water",
        "resources": {}
      },
      {
        "x": 17,
        "y": 12,
        "elevation": 0.18424748954473094,
        "terrain": "water",
        "resources": {}
      },
      {
        "x": 18,
        "y": 12,
        "elevation": 0.10918824253002415,
        "terrain": "water",
        "resources": {}
      },
      {
        "x": 19,
        "y": 12,
        "elevation": 0.05686273973665388,
        "terrain": "water",
        "resources": {}
      }
    ],
    [
      {
        "x": 0,
        "y": 13,
        "elevation": 0.029684146793202623,
        "terrain": "water",
        "resources": {}
      },
      {
        "x": 1,
        "y": 13,
        "elevation": 0.10600321313728342,
        "terrain": "water",
        "resources": {}
      },
      {
        "x": 2,
        "y": 13,
        "elevation": 0.15984529477298612,
        "terrain": "water",
        "resources": {}
      },
      {
        "x": 3,
        "y": 13,
        "elevation": 0.28628718499628963,
        "terrain": "beach",
        "resources": {}
      },
      {
        "x": 4,
        "y": 13,
        "elevation": 0.3210425894604698,
        "terrain": "grass",
        "resources": {}
      },
      {
        "x": 5,
        "y": 13,
        "elevation": 0.3404241096511912,
        "terrain": "grass",
        "resources": {}
      },
      {
        "x": 6,
        "y": 13,
        "elevation": 0.40600930888853926,
        "terrain": "grass",
        "resources": {}
      },
      {
        "x": 7,
        "y": 13,
        "elevation": 0.3927119806607382,
        "terrain": "grass",
        "resources": {
          "water": 1
        }
      },
      {
        "x": 8,
        "y": 13,
        "elevation": 0.47567295818819527,
        "terrain": "forest",
        "resources": {}
      },
      {
        "x": 9,
        "y": 13,
        "elevation": 0.45900818670139754,
        "terrain": "forest",
        "resources": {
          "wood": 1
        }
      },
      {
        "x": 10,
        "y": 13,
        "elevation": 0.3339292740367231,
        "terrain": "grass",
        "resources": {}
      },
      {
        "x": 11,
        "y": 13,
        "elevation": 0.3545259940797252,
        "terrain": "grass",
        "resources": {}
      },
      {
        "x": 12,
        "y": 13,
        "elevation": 0.37313321230019353,
        "terrain": "grass",
        "resources": {}
      },
      {
        "x": 13,
        "y": 13,
        "elevation": 0.3257013605119851,
        "terrain": "grass",
        "resources": {}
      },
      {
        "x": 14,
        "y": 13,
        "elevation": 0.25835776323217363,
        "terrain": "beach",
        "resources": {}
      },
      {
        "x": 15,
        "y": 13,
        "elevation": 0.2563689756778065,
        "terrain": "beach",
        "resources": {
          "food": 1
        }
      },
      {
        "x": 16,
        "y": 13,
        "elevation": 0.22626644037656798,
        "terrain": "water",
        "resources": {}
      },
      {
        "x": 17,
        "y": 13,
        "elevation": 0.1756694390020065,
        "terrain": "water",
        "resources": {}
      },
      {
        "x": 18,
        "y": 13,
        "elevation": 0.1065409557359415,
        "terrain": "water",
        "resources": {}
      },
      {
        "x": 19,
        "y": 13,
        "elevation": 0.03281499741960042,
        "terrain": "water",
        "resources": {}
      }
    ],
    [
      {
        "x": 0,
        "y": 14,
        "elevation": 0.0027704162034244925,
        "terrain": "water",
        "resources": {}
      },
      {
        "x": 1,
        "y": 14,
        "elevation": 0.06213719997315984,
        "terrain": "water",
        "resources": {}
      },
      {
        "x": 2,
        "y": 14,
        "elevation": 0.16212273820201298,
        "terrain": "water",
        "resources": {}
      },
      {
        "x": 3,
        "y": 14,
        "elevation": 0.26153110664826057,
        "terrain": "beach",
        "resources": {}
      },
      {
        "x": 4,
        "y": 14,
        "elevation": 0.35670931451020366,
        "terrain": "grass",
        "resources": {}
      },
      {
        "x": 5,
        "y": 14,
        "elevation": 0.3206913389064554,
        "terrain": "grass",
        "resources": {}
      },
      {
        "x": 6,
        "y": 14,
        "elevation": 0.32974719637730265,
        "terrain": "grass",
        "resources": {}
      },
      {
        "x": 7,
        "y": 14,
        "elevation": 0.36681877834149235,
        "terrain": "grass",
        "resources": {}
      },
      {
        "x": 8,
        "y": 14,
        "elevation": 0.3757148760423946,
        "terrain": "grass",
        "resources": {}
      },
      {
        "x": 9,
        "y": 14,
        "elevation": 0.3572457416925913,
        "terrain": "grass",
        "resources": {}
      },
      {
        "x": 10,
        "y": 14,
        "elevation": 0.3643097914981683,
        "terrain": "grass",
        "resources": {
          "water": 1
        }
      },
      {
        "x": 11,
        "y": 14,
        "elevation": 0.3231917889575838,
        "terrain": "grass",
        "resources": {}
      },
      {
        "x": 12,
        "y": 14,
        "elevation": 0.26341697657905233,
        "terrain": "beach",
        "resources": {}
      },
      {
        "x": 13,
        "y": 14,
        "elevation": 0.32917313616421257,
        "terrain": "grass",
        "resources": {}
      },
      {
        "x": 14,
        "y": 14,
        "elevation": 0.3227129848184919,
        "terrain": "grass",
        "resources": {}
      },
      {
        "x": 15,
        "y": 14,
        "elevation": 0.24475811197949435,
        "terrain": "water",
        "resources": {}
      },
      {
        "x": 16,
        "y": 14,
        "elevation": 0.18326633649401053,
        "terrain": "water",
        "resources": {}
      },
      {
        "x": 17,
        "y": 14,
        "elevation": 0.11765139821376429,
        "terrain": "water",
        "resources": {}
      },
      {
        "x": 18,
        "y": 14,
        "elevation": 0.07608180697109625,
        "terrain": "water",
        "resources": {}
      },
      {
        "x": 19,
        "y": 14,
        "elevation": 0.003600653327326109,
        "terrain": "water",
        "resources": {}
      }
    ],
    [
      {
        "x": 0,
        "y": 15,
        "elevation": 0,
        "terrain": "water",
        "resources": {}
      },
      {
        "x": 1,
        "y": 15,
        "elevation": 0.03448970183591575,
        "terrain": "water",
        "resources": {}
      },
      {
        "x": 2,
        "y": 15,
        "elevation": 0.11119206401423025,
        "terrain": "water",
        "resources": {}
      },
      {
        "x": 3,
        "y": 15,
        "elevation": 0.17239030308964745,
        "terrain": "water",
        "resources": {}
      },
      {
        "x": 4,
        "y": 15,
        "elevation": 0.25736318186380336,
        "terrain": "beach",
        "resources": {}
      },
      {
        "x": 5,
        "y": 15,
        "elevation": 0.2913317892909923,
        "terrain": "beach",
        "resources": {}
      },
      {
        "x": 6,
        "y": 15,
        "elevation": 0.2509383669426134,
        "terrain": "beach",
        "resources": {}
      },
      {
        "x": 7,
        "y": 15,
        "elevation": 0.25668824659590866,
        "terrain": "beach",
        "resources": {}
      },
      {
        "x": 8,
        "y": 15,
        "elevation": 0.2721366508044026,
        "terrain": "beach",
        "resources": {}
      },
      {
        "x": 9,
        "y": 15,
        "elevation": 0.32491532968796294,
        "terrain": "grass",
        "resources": {}
      },
      {
        "x": 10,
        "y": 15,
        "elevation": 0.2993969173770528,
        "terrain": "beach",
        "resources": {}
      },
      {
        "x": 11,
        "y": 15,
        "elevation": 0.2779513898034186,
        "terrain": "beach",
        "resources": {}
      },
      {
        "x": 12,
        "y": 15,
        "elevation": 0.24786883322513864,
        "terrain": "water",
        "resources": {}
      },
      {
        "x": 13,
        "y": 15,
        "elevation": 0.29866443543288673,
        "terrain": "beach",
        "resources": {}
      },
      {
        "x": 14,
        "y": 15,
        "elevation": 0.3295515733543401,
        "terrain": "grass",
        "resources": {}
      },
      {
        "x": 15,
        "y": 15,
        "elevation": 0.21985708060885917,
        "terrain": "water",
        "resources": {}
      },
      {
        "x": 16,
        "y": 15,
        "elevation": 0.15829049885440452,
        "terrain": "water",
        "resources": {}
      },
      {
        "x": 17,
        "y": 15,
        "elevation": 0.10130626023079975,
        "terrain": "water",
        "resources": {}
      },
      {
        "x": 18,
        "y": 15,
        "elevation": 0.03424649499559477,
        "terrain": "water",
        "resources": {}
      },
      {
        "x": 19,
        "y": 15,
        "elevation": 0,
        "terrain": "water",
        "resources": {}
      }
    ],
    [
      {
        "x": 0,
        "y": 16,
        "elevation": 0,
        "terrain": "water",
        "resources": {}
      },
      {
        "x": 1,
        "y": 16,
        "elevation": 0,
        "terrain": "water",
        "resources": {}
      },
      {
        "x": 2,
        "y": 16,
        "elevation": 0.04153554562861476,
        "terrain": "water",
        "resources": {}
      },
      {
        "x": 3,
        "y": 16,
        "elevation": 0.0917273735452658,
        "terrain": "water",
        "resources": {}
      },
      {
        "x": 4,
        "y": 16,
        "elevation": 0.15949763427002236,
        "terrain": "water",
        "resources": {}
      },
      {
        "x": 5,
        "y": 16,
        "elevation": 0.1861302638215067,
        "terrain": "water",
        "resources": {}
      },
      {
        "x": 6,
        "y": 16,
        "elevation": 0.19710129369198193,
        "terrain": "water",
        "resources": {}
      },
      {
        "x": 7,
        "y": 16,
        "elevation": 0.24938203754548538,
        "terrain": "water",
        "resources": {}
      },
      {
        "x": 8,
        "y": 16,
        "elevation": 0.2732145645647762,
        "terrain": "beach",
        "resources": {}
      },
      {
        "x": 9,
        "y": 16,
        "elevation": 0.3206355339777335,
        "terrain": "grass",
        "resources": {}
      },
      {
        "x": 10,
        "y": 16,
        "elevation": 0.2598531813860945,
        "terrain": "beach",
        "resources": {}
      },
      {
        "x": 11,
        "y": 16,
        "elevation": 0.2454962265997145,
        "terrain": "water",
        "resources": {}
      },
      {
        "x": 12,
        "y": 16,
        "elevation": 0.2546790424506219,
        "terrain": "beach",
        "resources": {}
      },
      {
        "x": 13,
        "y": 16,
        "elevation": 0.2684791648594286,
        "terrain": "beach",
        "resources": {}
      },
      {
        "x": 14,
        "y": 16,
        "elevation": 0.2408950575643258,
        "terrain": "water",
        "resources": {}
      },
      {
        "x": 15,
        "y": 16,
        "elevation": 0.16381478615586734,
        "terrain": "water",
        "resources": {}
      },
      {
        "x": 16,
        "y": 16,
        "elevation": 0.10073381975934494,
        "terrain": "water",
        "resources": {}
      },
      {
        "x": 17,
        "y": 16,
        "elevation": 0.04452142789304323,
        "terrain": "water",
        "resources": {}
      },
      {
        "x": 18,
        "y": 16,
        "elevation": 0,
        "terrain": "water",
        "resources": {}
      },
      {
        "x": 19,
        "y": 16,
        "elevation": 0,
        "terrain": "water",
        "resources": {}
      }
    ],
    [
      {
        "x": 0,
        "y": 17,
        "elevation": 0,
        "terrain": "water",
        "resources": {}
      },
      {
        "x": 1,
        "y": 17,
        "elevation": 0,
        "terrain": "water",
        "resources": {}
      },
      {
        "x": 2,
        "y": 17,
        "elevation": 0,
        "terrain": "water",
        "resources": {}
      },
      {
        "x": 3,
        "y": 17,
        "elevation": 0.04698139582475652,
        "terrain": "water",
        "resources": {}
      },
      {
        "x": 4,
        "y": 17,
        "elevation": 0.08035839623595127,
        "terrain": "water",
        "resources": {}
      },
      {
        "x": 5,
        "y": 17,
        "elevation": 0.11118417876134896,
        "terrain": "water",
        "resources": {}
      },
      {
        "x": 6,
        "y": 17,
        "elevation": 0.14824055817291606,
        "terrain": "water",
        "resources": {}
      },
      {
        "x": 7,
        "y": 17,
        "elevation": 0.16633638317292201,
        "terrain": "water",
        "resources": {}
      },
      {
        "x": 8,
        "y": 17,
        "elevation": 0.26272821255252865,
        "terrain": "beach",
        "resources": {}
      },
      {
        "x": 9,
        "y": 17,
        "elevation": 0.27636361302569584,
        "terrain": "beach",
        "resources": {}
      },
      {
        "x": 10,
        "y": 17,
        "elevation": 0.227704863123112,
        "terrain": "water",
        "resources": {}
      },
      {
        "x": 11,
        "y": 17,
        "elevation": 0.18227059052355066,
        "terrain": "water",
        "resources": {}
      },
      {
        "x": 12,
        "y": 17,
        "elevation": 0.18421993675043666,
        "terrain": "water",
        "resources": {}
      },
      {
        "x": 13,
        "y": 17,
        "elevation": 0.18798461578685127,
        "terrain": "water",
        "resources": {}
      },
      {
        "x": 14,
        "y": 17,
        "elevation": 0.15124598680893533,
        "terrain": "water",
        "resources": {}
      },
      {
        "x": 15,
        "y": 17,
        "elevation": 0.08415166858344306,
        "terrain": "water",
        "resources": {}
      },
      {
        "x": 16,
        "y": 17,
        "elevation": 0.03700642194472757,
        "terrain": "water",
        "resources": {}
      },
      {
        "x": 17,
        "y": 17,
        "elevation": 0,
        "terrain": "water",
        "resources": {}
      },
      {
        "x": 18,
        "y": 17,
        "elevation": 0,
        "terrain": "water",
        "resources": {}
      },
      {
        "x": 19,
        "y": 17,
        "elevation": 0,
        "terrain": "water",
        "resources": {}
      }
    ],
    [
      {
        "x": 0,
        "y": 18,
        "elevation": 0,
        "terrain": "water",
        "resources": {}
      },
      {
        "x": 1,
        "y": 18,
        "elevation": 0,
        "terrain": "water",
        "resources": {}
      },
      {
        "x": 2,
        "y": 18,
        "elevation": 0,
        "terrain": "water",
        "resources": {}
      },
      {
        "x": 3,
        "y": 18,
        "elevation": 0,
        "terrain": "water",
        "resources": {}
      },
      {
        "x": 4,
        "y": 18,
        "elevation": 0.032071359431906504,
        "terrain": "water",
        "resources": {}
      },
      {
        "x": 5,
        "y": 18,
        "elevation": 0.0686143981800524,
        "terrain": "water",
        "resources": {}
      },
      {
        "x": 6,
        "y": 18,
        "elevation": 0.093225945895949,
        "terrain": "water",
        "resources": {}
      },
      {
        "x": 7,
        "y": 18,
        "elevation": 0.10997531248303294,
        "terrain": "water",
        "resources": {}
      },
      {
        "x": 8,
        "y": 18,
        "elevation": 0.13570841013900245,
        "terrain": "water",
        "resources": {}
      },
      {
        "x": 9,
        "y": 18,
        "elevation": 0.1587076542602095,
        "terrain": "water",
        "resources": {}
      },
      {
        "x": 10,
        "y": 18,
        "elevation": 0.1337515851522,
        "terrain": "water",
        "resources": {}
      },
      {
        "x": 11,
        "y": 18,
        "elevation": 0.12438409565100929,
        "terrain": "water",
        "resources": {}
      },
      {
        "x": 12,
        "y": 18,
        "elevation": 0.10818055109851753,
        "terrain": "water",
        "resources": {}
      },
      {
        "x": 13,
        "y": 18,
        "elevation": 0.10263154595768494,
        "terrain": "water",
        "resources": {}
      },
      {
        "x": 14,
        "y": 18,
        "elevation": 0.07535285568886907,
        "terrain": "water",
        "resources": {}
      },
      {
        "x": 15,
        "y": 18,
        "elevation": 0.02645369707962594,
        "terrain": "water",
        "resources": {}
      },
      {
        "x": 16,
        "y": 18,
        "elevation": 0,
        "terrain": "water",
        "resources": {}
      },
      {
        "x": 17,
        "y": 18,
        "elevation": 0,
        "terrain": "water",
        "resources": {}
      },
      {
        "x": 18,
        "y": 18,
        "elevation": 0,
        "terrain": "water",
        "resources": {}
      },
      {
        "x": 19,
        "y": 18,
        "elevation": 0,
        "terrain": "water",
        "resources": {}
      }
    ],
    [
      {
        "x": 0,
        "y": 19,
        "elevation": 0,
        "terrain": "water",
        "resources": {}
      },
      {
        "x": 1,
        "y": 19,
        "elevation": 0,
        "terrain": "water",
        "resources": {}
      },
      {
        "x": 2,
        "y": 19,
        "elevation": 0,
        "terrain": "water",
        "resources": {}
      },
      {
        "x": 3,
        "y": 19,
        "elevation": 0,
        "terrain": "water",
        "resources": {}
      },
      {
        "x": 4,
        "y": 19,
        "elevation": 0,
        "terrain": "water",
        "resources": {}
      },
      {
        "x": 5,
        "y": 19,
        "elevation": 0.0029905398088922387,
        "terrain": "water",
        "resources": {}
      },
      {
        "x": 6,
        "y": 19,
        "elevation": 0.025743927800563504,
        "terrain": "water",
        "resources": {}
      },
      {
        "x": 7,
        "y": 19,
        "elevation": 0.048953327607158384,
        "terrain": "water",
        "resources": {}
      },
      {
        "x": 8,
        "y": 19,
        "elevation": 0.06310462032682168,
        "terrain": "water",
        "resources": {}
      },
      {
        "x": 9,
        "y": 19,
        "elevation": 0.08293170403317433,
        "terrain": "water",
        "resources": {}
      },
      {
        "x": 10,
        "y": 19,
        "elevation": 0.0598339806814653,
        "terrain": "water",
        "resources": {}
      },
      {
        "x": 11,
        "y": 19,
        "elevation": 0.054182672384569724,
        "terrain": "water",
        "resources": {}
      },
      {
        "x": 12,
        "y": 19,
        "elevation": 0.053824888249240734,
        "terrain": "water",
        "resources": {}
      },
      {
        "x": 13,
        "y": 19,
        "elevation": 0.033234820552573666,
        "terrain": "water",
        "resources": {}
      },
      {
        "x": 14,
        "y": 19,
        "elevation": 0.003157350863873466,
        "terrain": "water",
        "resources": {}
      },
      {
        "x": 15,
        "y": 19,
        "elevation": 0,
        "terrain": "water",
        "resources": {}
      },
      {
        "x": 16,
        "y": 19,
        "elevation": 0,
        "terrain": "water",
        "resources": {}
      },
      {
        "x": 17,
        "y": 19,
        "elevation": 0,
        "terrain": "water",
        "resources": {}
      },
      {
        "x": 18,
        "y": 19,
        "elevation": 0,
        "terrain": "water",
        "resources": {}
      },
      {
        "x": 19,
        "y": 19,
        "elevation": 0,
        "terrain": "water",
        "resources": {}
      }
    ]
  ],
  "agents": [
    {
      "id": "agent_001",
      "name": "Alice",
      "gender": "female",
      "age": 1130,
      "status": "adult",
      "happiness": 87,
      "personality": {
        "openness": 71,
        "conscientiousness": 89,
        "extraversion": 51,
        "agreeableness": 52,
        "neuroticism": 26
      },
      "memory": [
        {
          "tick": 0,
          "eventId": "godmsg_1770879282767_lq9yt8",
          "description": "[GOD] Greetings, agents! I am watching over you. Work together and survive!"
        }
      ],
      "relationships": [],
      "inventory": {
        "wood": 1,
        "stone": 0,
        "water": 1,
        "food": 13,
        "tools": 1
      },
      "mealsEaten": 3,
      "lastMealTick": 0,
      "starving": false,
      "alive": true,
      "location": {
        "x": 14,
        "y": 7
      },
      "visibilityRadius": 3,
      "conversationHistory": {}
    },
    {
      "id": "agent_002",
      "name": "Bob",
      "gender": "male",
      "age": 1454,
      "status": "adult",
      "happiness": 98,
      "personality": {
        "openness": 25,
        "conscientiousness": 63,
        "extraversion": 47,
        "agreeableness": 84,
        "neuroticism": 59
      },
      "memory": [
        {
          "tick": 0,
          "eventId": "godmsg_1770879282767_5xhcny",
          "description": "[GOD] Greetings, agents! I am watching over you. Work together and survive!"
        }
      ],
      "relationships": [],
      "inventory": {
        "wood": 3,
        "stone": 1,
        "water": 1,
        "food": 16,
        "tools": 1
      },
      "mealsEaten": 3,
      "lastMealTick": 0,
      "starving": false,
      "alive": true,
      "location": {
        "x": 14,
        "y": 14
      },
      "visibilityRadius": 3,
      "conversationHistory": {}
    },
    {
      "id": "agent_003",
      "name": "Carol",
      "gender": "female",
      "age": 1169,
      "status": "adult",
      "happiness": 97,
      "personality": {
        "openness": 64,
        "conscientiousness": 37,
        "extraversion": 42,
        "agreeableness": 22,
        "neuroticism": 86
      },
      "memory": [
        {
          "tick": 0,
          "eventId": "godmsg_1770879282767_wy7zel",
          "description": "[GOD] Greetings, agents! I am watching over you. Work together and survive!"
        }
      ],
      "relationships": [],
      "inventory": {
        "wood": 3,
        "stone": 0,
        "water": 3,
        "food": 16,
        "tools": 0
      },
      "mealsEaten": 3,
      "lastMealTick": 0,
      "starving": false,
      "alive": true,
      "location": {
        "x": 7,
        "y": 11
      },
      "visibilityRadius": 3,
      "conversationHistory": {}
    },
    {
      "id": "agent_004",
      "name": "David",
      "gender": "male",
      "age": 1206,
      "status": "adult",
      "happiness": 83,
      "personality": {
        "openness": 13,
        "conscientiousness": 43,
        "extraversion": 33,
        "agreeableness": 65,
        "neuroticism": 13
      },
      "memory": [
        {
          "tick": 0,
          "eventId": "godmsg_1770879282767_agdwa5",
          "description": "[GOD] Greetings, agents! I am watching over you. Work together and survive!"
        }
      ],
      "relationships": [],
      "inventory": {
        "wood": 2,
        "stone": 1,
        "water": 2,
        "food": 12,
        "tools": 1
      },
      "mealsEaten": 3,
      "lastMealTick": 0,
      "starving": false,
      "alive": true,
      "location": {
        "x": 12,
        "y": 8
      },
      "visibilityRadius": 3,
      "conversationHistory": {}
    },
    {
      "id": "agent_005",
      "name": "Eve",
      "gender": "female",
      "age": 1016,
      "status": "adult",
      "happiness": 84,
      "personality": {
        "openness": 79,
        "conscientiousness": 62,
        "extraversion": 16,
        "agreeableness": 27,
        "neuroticism": 91
      },
      "memory": [
        {
          "tick": 0,
          "eventId": "godmsg_1770879282767_cesa9u",
          "description": "[GOD] Greetings, agents! I am watching over you. Work together and survive!"
        }
      ],
      "relationships": [],
      "inventory": {
        "wood": 0,
        "stone": 0,
        "water": 0,
        "food": 15,
        "tools": 0
      },
      "mealsEaten": 3,
      "lastMealTick": 0,
      "starving": false,
      "alive": true,
      "location": {
        "x": 9,
        "y": 14
      },
      "visibilityRadius": 3,
      "conversationHistory": {}
    },
    {
      "id": "agent_006",
      "name": "Frank",
      "gender": "male",
      "age": 68,
      "status": "child",
      "happiness": 79,
      "personality": {
        "openness": 59,
        "conscientiousness": 65,
        "extraversion": 79,
        "agreeableness": 54,
        "neuroticism": 84
      },
      "memory": [
        {
          "tick": 0,
          "eventId": "godmsg_1770879282767_wy1e9d",
          "description": "[GOD] Greetings, agents! I am watching over you. Work together and survive!"
        }
      ],
      "relationships": [],
      "inventory": {
        "wood": 3,
        "stone": 1,
        "water": 3,
        "food": 19,
        "tools": 0
      },
      "mealsEaten": 3,
      "lastMealTick": 0,
      "starving": false,
      "alive": true,
      "location": {
        "x": 9,
        "y": 16
      },
      "visibilityRadius": 3,
      "conversationHistory": {}
    },
    {
      "id": "agent_007",
      "name": "Grace",
      "gender": "female",
      "age": 1470,
      "status": "adult",
      "happiness": 76,
      "personality": {
        "openness": 67,
        "conscientiousness": 28,
        "extraversion": 8,
        "agreeableness": 61,
        "neuroticism": 62
      },
      "memory": [
        {
          "tick": 0,
          "eventId": "godmsg_1770879282767_vmozbq",
          "description": "[GOD] Greetings, agents! I am watching over you. Work together and survive!"
        }
      ],
      "relationships": [],
      "inventory": {
        "wood": 4,
        "stone": 2,
        "water": 3,
        "food": 11,
        "tools": 0
      },
      "mealsEaten": 3,
      "lastMealTick": 0,
      "starving": false,
      "alive": true,
      "location": {
        "x": 13,
        "y": 11
      },
      "visibilityRadius": 3,
      "conversationHistory": {}
    },
    {
      "id": "agent_008",
      "name": "Henry",
      "gender": "male",
      "age": 1130,
      "status": "adult",
      "happiness": 78,
      "personality": {
        "openness": 30,
        "conscientiousness": 25,
        "extraversion": 25,
        "agreeableness": 24,
        "neuroticism": 52
      },
      "memory": [
        {
          "tick": 0,
          "eventId": "godmsg_1770879282767_47vblz",
          "description": "[GOD] Greetings, agents! I am watching over you. Work together and survive!"
        }
      ],
      "relationships": [],
      "inventory": {
        "wood": 2,
        "stone": 0,
        "water": 3,
        "food": 15,
        "tools": 1
      },
      "mealsEaten": 3,
      "lastMealTick": 0,
      "starving": false,
      "alive": true,
      "location": {
        "x": 7,
        "y": 6
      },
      "visibilityRadius": 3,
      "conversationHistory": {}
    }
  ],
  "droppedItems": [],
  "weather": "rain",
  "time": 0,
  "dayNight": "day"
}